dab/__init__.py
dab/__main__.py
dab/__version__.py
dab/core.py
dab/dns.py
dab/netbios.py
dab/ssh.py
dab-1.0.1.dist-info/LICENSE
dab-1.0.1.dist-info/METADATA
dab-1.0.1.dist-info/WHEEL
dab-1.0.1.dist-info/entry_points.txt
dab-1.0.1.dist-info/top_level.txt
dab-1.0.1.dist-info/RECORD
